{
  "teamId": "TEAM_KBL_ROYALLIONS_1",
  "farmTeamId": "TEAM_KBL_ROYALLIONS_2",
  "name": "대구 로얄라이온스",
  "nameEn": "Daegu Royal Lions",
  "city": "대구",
  "cityEn": "Daegu",
  "budgetTier": "mid",
  "rosterPolicy": {
    "active": 35,
    "farm": 30
  },
  "salaryCap": 3500000,
  "currentPayroll": 0,
  "stadium": "대구 라이온 구장",
  "colors": [
    "#880e4f",
    "#ffd600"
  ],
  "roster": {
    "active": [
      "PLY_00686",
      "PLY_00687",
      "PLY_00688",
      "PLY_00689",
      "PLY_00690",
      "PLY_00691",
      "PLY_00692",
      "PLY_00693",
      "PLY_00694",
      "PLY_00695",
      "PLY_00696",
      "PLY_00697",
      "PLY_00698",
      "PLY_00699",
      "PLY_00700",
      "PLY_00701",
      "PLY_00702",
      "PLY_00703",
      "PLY_00704",
      "PLY_00705",
      "PLY_00706",
      "PLY_00707",
      "PLY_00708",
      "PLY_00709",
      "PLY_00710",
      "PLY_01962",
      "PLY_01963",
      "PLY_01964",
      "PLY_01965",
      "PLY_01966",
      "PLY_01967",
      "PLY_01968",
      "PLY_01969",
      "PLY_01970",
      "PLY_01971"
    ],
    "farm": [
      "PLY_00711",
      "PLY_00712",
      "PLY_00713",
      "PLY_00714",
      "PLY_00715",
      "PLY_00716",
      "PLY_00717",
      "PLY_00718",
      "PLY_00719",
      "PLY_00720",
      "PLY_00721",
      "PLY_00722",
      "PLY_00723",
      "PLY_00724",
      "PLY_00725",
      "PLY_00726",
      "PLY_00727",
      "PLY_00728",
      "PLY_00729",
      "PLY_00730",
      "PLY_01972",
      "PLY_01973",
      "PLY_01974",
      "PLY_01975",
      "PLY_01976",
      "PLY_01977",
      "PLY_01978",
      "PLY_01979",
      "PLY_01980",
      "PLY_01981"
    ],
    "rotation": [],
    "lineup": [],
    "bullpen": []
  }
}